utilsj/__init__.py
utilsj/concurrency.py
utilsj/files.py
utilsj/helper.py
utilsj/loan.py
utilsj/pdf.py
utilsj/timer.py
utilsj/video.py
utilsj-0.0.24.dist-info/LICENSE
utilsj-0.0.24.dist-info/METADATA
utilsj-0.0.24.dist-info/WHEEL
utilsj-0.0.24.dist-info/top_level.txt
utilsj-0.0.24.dist-info/RECORD
