Metadata-Version: 2.1
Name: utilsj
Version: 0.0.24
Summary: A personal kit
Author-email: zjj421 <zhangjian421wo@outlook.com>
Project-URL: Homepage, https://github.com/zjj421/zj_utils
Project-URL: Bug Tracker, https://github.com/zjj421/zj_utils/issues
Classifier: Programming Language :: Python :: 3
Classifier: License :: OSI Approved :: MIT License
Classifier: Operating System :: OS Independent
Requires-Python: >=3.7
License-File: LICENSE
